wkbparse-0.2.0.dist-info/METADATA
wkbparse-0.2.0.dist-info/WHEEL
wkbparse-0.2.0.dist-info/licenses/LICENSE
wkbparse.libs/libgcc_s-5b5488a6.so.1
wkbparse/py.typed
wkbparse/__init__.py
wkbparse/wkbparse.pyi
wkbparse/wkbparse.cpython-39-arm-linux-gnueabihf.so
wkbparse-0.2.0.dist-info/RECORD
