Metadata-Version: 2.4
Name: wkbparse
Version: 0.2.0
Classifier: Programming Language :: Rust
Classifier: Programming Language :: Python :: 3
Classifier: Programming Language :: Python :: Implementation :: CPython
Classifier: Programming Language :: Python :: Implementation :: PyPy
Classifier: Topic :: Scientific/Engineering :: GIS
Classifier: Development Status :: 4 - Beta
Classifier: License :: OSI Approved :: MIT License
License-File: LICENSE
Summary: EWKB and TWKB parsing and conversion to GeoJSON
Keywords: PostgreSQL,PostGIS,GIS,GEO,WKB,TWKB,GeoJSON
Home-Page: https://github.com/arjuote/wkbparse
Author: Arsi Juote <arsi.juote@gmail.com>
Author-email: Arsi Juote <arsi.juote@gmail.com>
License: MIT
Requires-Python: >=3.8
Project-URL: Source, https://github.com/arjuote/wkbparse
